hatch_pinned_extra/__init__.py
hatch_pinned_extra/py.typed
hatch_pinned_extra-0.0.3.dist-info/METADATA
hatch_pinned_extra-0.0.3.dist-info/WHEEL
hatch_pinned_extra-0.0.3.dist-info/entry_points.txt
hatch_pinned_extra-0.0.3.dist-info/licenses/LICENSE
hatch_pinned_extra-0.0.3.dist-info/RECORD
