Metadata-Version: 2.4
Name: hatch-pinned-extra
Version: 0.0.3
Summary: Add a packaging extra with pinned dependencies from a lock file
Author-email: Edgar Ramírez Mondragón <edgarrm358@gmail.com>
License-Expression: MIT
License-File: LICENSE
Classifier: Programming Language :: Python :: 3
Classifier: Programming Language :: Python :: 3.9
Classifier: Programming Language :: Python :: 3.10
Classifier: Programming Language :: Python :: 3.11
Classifier: Programming Language :: Python :: 3.12
Classifier: Programming Language :: Python :: 3.13
Classifier: Programming Language :: Python :: 3.14
Classifier: Programming Language :: Python :: 3.15
Requires-Python: >=3.9
Requires-Dist: hatchling>=1.27.0
Requires-Dist: packaging>=24.2
Requires-Dist: tomli>=1.2.2; python_version < '3.11'
Requires-Dist: typing-extensions>=4.4; python_version < '3.10'
